[
    {
        "id": "47045",
        "hometeam": {
            "id": "4457",
            "name": "AG超玩会",
            "score": 1,
            "ban": [],
            "pick": [
                {
                    "user": "30818",
                    "user_name": "晴天",
                    "hero": "134",
                    "equ": [
                        "1422",
                        "1333",
                        "1137",
                        "1138",
                        "1332",
                        "1335"
                    ],
                    "kda": "1/4/4",
                    "money": "16067",
                    "damage": "52808",
                    "endure": "118444"
                },
                {
                    "user": "26351",
                    "user_name": "Vv",
                    "hero": "139",
                    "equ": [
                        "1337",
                        "1422",
                        "1126",
                        "1333",
                        "1335",
                        "1131"
                    ],
                    "kda": "2/2/8",
                    "money": "16048",
                    "damage": "69521",
                    "endure": "87804"
                },
                {
                    "user": "26352",
                    "user_name": "梦泪",
                    "hero": "199",
                    "equ": [
                        "1127",
                        "1328",
                        "1126",
                        "1141",
                        "1131",
                        "1135"
                    ],
                    "kda": "1/3/8",
                    "money": "15541",
                    "damage": "85370",
                    "endure": "81515"
                },
                {
                    "user": "28923",
                    "user_name": "小飞",
                    "hero": "190",
                    "equ": [
                        "1337",
                        "1231",
                        "1240",
                        "1238",
                        "1232",
                        "1233"
                    ],
                    "kda": "10/1/4",
                    "money": "16907",
                    "damage": "145555",
                    "endure": "86977"
                },
                {
                    "user": "26413",
                    "user_name": "月痕",
                    "hero": "186",
                    "equ": [
                        "1724",
                        "1422",
                        "1333",
                        "1332",
                        "1335"
                    ],
                    "kda": "2/3/5",
                    "money": "10778",
                    "damage": "26961",
                    "endure": "157059"
                }
            ]
        },
        "guesteam": {
            "id": "4476",
            "name": "YTG",
            "score": 0,
            "ban": [],
            "pick": [
                {
                    "user": "140",
                    "user_name": "路西法",
                    "hero": "140",
                    "equ": [
                        "1422",
                        "1338",
                        "1137",
                        "1332",
                        "1335",
                        "1337"
                    ],
                    "kda": "2/3/5",
                    "money": "13186",
                    "damage": "75120",
                    "endure": "130026"
                },
                {
                    "user": "178",
                    "user_name": "小壳",
                    "hero": "178",
                    "equ": [
                        "1422",
                        "1327",
                        "1137",
                        "1124",
                        "1138",
                        "1334"
                    ],
                    "kda": "2/4/7",
                    "money": "11385",
                    "damage": "49965",
                    "endure": "79276"
                },
                {
                    "user": "502",
                    "user_name": "夏天",
                    "hero": "502",
                    "equ": [
                        "1533",
                        "1337",
                        "1126",
                        "1137",
                        "1134",
                        "1131"
                    ],
                    "kda": "5/2/4",
                    "money": "13590",
                    "damage": "92119",
                    "endure": "78638"
                },
                {
                    "user": "110",
                    "user_name": "橙汁",
                    "hero": "110",
                    "equ": [
                        "1423",
                        "1233",
                        "1235",
                        "1232",
                        "1231",
                        "1238"
                    ],
                    "kda": "2/2/10",
                    "money": "13577",
                    "damage": "160355",
                    "endure": "45761"
                },
                {
                    "user": "168",
                    "user_name": "落幕",
                    "hero": "168",
                    "equ": [
                        "1722",
                        "1422",
                        "1333",
                        "1335",
                        "1337",
                        "1321"
                    ],
                    "kda": "2/5/9",
                    "money": "10303",
                    "damage": "36293",
                    "endure": "115844"
                }
            ]
        }
    },
    {
        "id": "47042",
        "hometeam": {
            "id": "4457",
            "name": "AG超玩会",
            "score": 0,
            "ban": [],
            "pick": [
                {
                    "user": "30818",
                    "user_name": "晴天",
                    "hero": "171",
                    "equ": [
                        "1422",
                        "1314",
                        "1335",
                        "1331",
                        "1327",
                        "1311"
                    ],
                    "kda": "0/2/6",
                    "money": "7532",
                    "damage": "39869",
                    "endure": "85921"
                },
                {
                    "user": "26351",
                    "user_name": "Vv",
                    "hero": "140",
                    "equ": [
                        "1422",
                        "1333",
                        "1335",
                        "1124",
                        "1327"
                    ],
                    "kda": "1/3/6",
                    "money": "8377",
                    "damage": "40061",
                    "endure": "51190"
                },
                {
                    "user": "26352",
                    "user_name": "梦泪",
                    "hero": "199",
                    "equ": [
                        "1523",
                        "1422",
                        "1126",
                        "1133",
                        "1131",
                        "1135"
                    ],
                    "kda": "0/3/5",
                    "money": "9846",
                    "damage": "45099",
                    "endure": "38946"
                },
                {
                    "user": "28923",
                    "user_name": "小飞",
                    "hero": "190",
                    "equ": [
                        "1422",
                        "1235",
                        "1511",
                        "1240",
                        "1239",
                        "1232"
                    ],
                    "kda": "6/1/3",
                    "money": "9740",
                    "damage": "89347",
                    "endure": "42490"
                },
                {
                    "user": "26413",
                    "user_name": "月痕",
                    "hero": "168",
                    "equ": [
                        "1713",
                        "1422",
                        "1333",
                        "1313",
                        "1332",
                        "1311"
                    ],
                    "kda": "2/2/5",
                    "money": "6884",
                    "damage": "23542",
                    "endure": "72525"
                }
            ]
        },
        "guesteam": {
            "id": "4476",
            "name": "YTG",
            "score": 1,
            "ban": [],
            "pick": [
                {
                    "user": "139",
                    "user_name": "路西法",
                    "hero": "139",
                    "equ": [
                        "1422",
                        "1131",
                        "1126",
                        "1114",
                        "1333",
                        "1321"
                    ],
                    "kda": "3/3/5",
                    "money": "8923",
                    "damage": "45241",
                    "endure": "69768"
                },
                {
                    "user": "194",
                    "user_name": "小壳",
                    "hero": "194",
                    "equ": [
                        "1425",
                        "1137",
                        "1331",
                        "1511",
                        "1133",
                        "1334"
                    ],
                    "kda": "3/1/5",
                    "money": "9813",
                    "damage": "37026",
                    "endure": "81808"
                },
                {
                    "user": "502",
                    "user_name": "夏天",
                    "hero": "502",
                    "equ": [
                        "1522",
                        "1425",
                        "1126",
                        "1134",
                        "1131",
                        "1121"
                    ],
                    "kda": "3/2/2",
                    "money": "9904",
                    "damage": "51430",
                    "endure": "64198"
                },
                {
                    "user": "176",
                    "user_name": "橙汁",
                    "hero": "176",
                    "equ": [
                        "1423",
                        "1236",
                        "1511",
                        "1235",
                        "1232",
                        "1239"
                    ],
                    "kda": "2/1/6",
                    "money": "9648",
                    "damage": "85858",
                    "endure": "42775"
                },
                {
                    "user": "126",
                    "user_name": "落幕",
                    "hero": "126",
                    "equ": [
                        "1722",
                        "1422",
                        "1333",
                        "1312",
                        "1334"
                    ],
                    "kda": "0/2/9",
                    "money": "7205",
                    "damage": "25394",
                    "endure": "62525"
                }
            ]
        }
    },
    {
        "id": "47041",
        "hometeam": {
            "id": "4457",
            "name": "AG超玩会",
            "score": 1,
            "ban": [],
            "pick": [
                {
                    "user": "30818",
                    "user_name": "晴天",
                    "hero": "120",
                    "equ": [
                        "1422",
                        "1314",
                        "1334",
                        "1327",
                        "1331",
                        "1325"
                    ],
                    "kda": "3/5/13",
                    "money": "8369",
                    "damage": "41381",
                    "endure": "93072"
                },
                {
                    "user": "26351",
                    "user_name": "Vv",
                    "hero": "140",
                    "equ": [
                        "1422",
                        "1333",
                        "1335",
                        "1137",
                        "1327"
                    ],
                    "kda": "7/4/9",
                    "money": "10085",
                    "damage": "67929",
                    "endure": "60238"
                },
                {
                    "user": "26352",
                    "user_name": "梦泪",
                    "hero": "199",
                    "equ": [
                        "1523",
                        "1422",
                        "1126",
                        "1133",
                        "1131",
                        "1135"
                    ],
                    "kda": "6/3/10",
                    "money": "9867",
                    "damage": "87019",
                    "endure": "42548"
                },
                {
                    "user": "28923",
                    "user_name": "小飞",
                    "hero": "115",
                    "equ": [
                        "1422",
                        "1235",
                        "1240",
                        "1511",
                        "12211",
                        "1239"
                    ],
                    "kda": "5/3/14",
                    "money": "9841",
                    "damage": "99935",
                    "endure": "45912"
                },
                {
                    "user": "26413",
                    "user_name": "月痕",
                    "hero": "194",
                    "equ": [
                        "1712",
                        "1422",
                        "1333",
                        "1332",
                        "1323"
                    ],
                    "kda": "1/2/17",
                    "money": "7652",
                    "damage": "38928",
                    "endure": "112189"
                }
            ]
        },
        "guesteam": {
            "id": "4476",
            "name": "YTG",
            "score": 0,
            "ban": [],
            "pick": [
                {
                    "user": "139",
                    "user_name": "路西法",
                    "hero": "139",
                    "equ": [
                        "1421",
                        "1131",
                        "1126",
                        "1333",
                        "1112",
                        "1313"
                    ],
                    "kda": "3/5/4",
                    "money": "8494",
                    "damage": "43146",
                    "endure": "73238"
                },
                {
                    "user": "126",
                    "user_name": "夏天",
                    "hero": "126",
                    "equ": [
                        "1421",
                        "1334",
                        "1331",
                        "1325",
                        "1335",
                        "1311"
                    ],
                    "kda": "2/5/9",
                    "money": "7997",
                    "damage": "58601",
                    "endure": "116576"
                },
                {
                    "user": "195",
                    "user_name": "小智",
                    "hero": "195",
                    "equ": [
                        "1522",
                        "1425",
                        "1132",
                        "1138",
                        "1137",
                        "1323"
                    ],
                    "kda": "6/4/7",
                    "money": "9333",
                    "damage": "64144",
                    "endure": "66875"
                },
                {
                    "user": "176",
                    "user_name": "橙汁",
                    "hero": "176",
                    "equ": [
                        "1422",
                        "1236",
                        "1235",
                        "1232",
                        "1214",
                        "1211"
                    ],
                    "kda": "3/3/5",
                    "money": "8730",
                    "damage": "57311",
                    "endure": "44508"
                },
                {
                    "user": "186",
                    "user_name": "落幕",
                    "hero": "186",
                    "equ": [
                        "1722",
                        "1426",
                        "1334",
                        "1333",
                        "1312"
                    ],
                    "kda": "1/5/9",
                    "money": "7290",
                    "damage": "33021",
                    "endure": "89702"
                }
            ]
        }
    },
    {
        "id": "47040",
        "hometeam": {
            "id": "4457",
            "name": "AG超玩会",
            "score": 1,
            "ban": [],
            "pick": [
                {
                    "user": "30818",
                    "user_name": "晴天",
                    "hero": "194",
                    "equ": [
                        "1422",
                        "1331",
                        "1334",
                        "1333",
                        "1312",
                        "1312"
                    ],
                    "kda": "0/1/10",
                    "money": "8576",
                    "damage": "34958",
                    "endure": "82513"
                },
                {
                    "user": "26351",
                    "user_name": "Vv",
                    "hero": "154",
                    "equ": [
                        "1421",
                        "1137",
                        "1325",
                        "1335",
                        "1327",
                        "1131"
                    ],
                    "kda": "4/2/8",
                    "money": "9875",
                    "damage": "56459",
                    "endure": "42639"
                },
                {
                    "user": "26352",
                    "user_name": "梦泪",
                    "hero": "502",
                    "equ": [
                        "1523",
                        "1422",
                        "1126",
                        "1134",
                        "1131",
                        "1121"
                    ],
                    "kda": "6/1/4",
                    "money": "10731",
                    "damage": "88390",
                    "endure": "42371"
                },
                {
                    "user": "28923",
                    "user_name": "小飞",
                    "hero": "190",
                    "equ": [
                        "1422",
                        "1235",
                        "1240",
                        "1511",
                        "1239",
                        "1221"
                    ],
                    "kda": "3/2/9",
                    "money": "8859",
                    "damage": "80726",
                    "endure": "48598"
                },
                {
                    "user": "26413",
                    "user_name": "月痕",
                    "hero": "186",
                    "equ": [
                        "1713",
                        "1422",
                        "1333",
                        "1313",
                        "1332"
                    ],
                    "kda": "0/3/7",
                    "money": "6630",
                    "damage": "17838",
                    "endure": "63574"
                }
            ]
        },
        "guesteam": {
            "id": "4476",
            "name": "YTG",
            "score": 0,
            "ban": [],
            "pick": [
                {
                    "user": "140",
                    "user_name": "路西法",
                    "hero": "140",
                    "equ": [
                        "1422",
                        "1333",
                        "1701",
                        "1332",
                        "1335",
                        "1124"
                    ],
                    "kda": "3/2/4",
                    "money": "8565",
                    "damage": "36543",
                    "endure": "76052"
                },
                {
                    "user": "199",
                    "user_name": "夏天",
                    "hero": "199",
                    "equ": [
                        "1523",
                        "1422",
                        "1126",
                        "1133",
                        "1131",
                        "1112"
                    ],
                    "kda": "3/3/6",
                    "money": "8747",
                    "damage": "69945",
                    "endure": "47583"
                },
                {
                    "user": "126",
                    "user_name": "小智",
                    "hero": "126",
                    "equ": [
                        "1422",
                        "1331",
                        "1335",
                        "1327",
                        "1111",
                        "1111"
                    ],
                    "kda": "1/3/7",
                    "money": "7503",
                    "damage": "45083",
                    "endure": "78640"
                },
                {
                    "user": "176",
                    "user_name": "橙汁",
                    "hero": "176",
                    "equ": [
                        "1423",
                        "1223",
                        "1235",
                        "1232",
                        "1239"
                    ],
                    "kda": "2/2/5",
                    "money": "8092",
                    "damage": "49180",
                    "endure": "46970"
                },
                {
                    "user": "168",
                    "user_name": "落幕",
                    "hero": "168",
                    "equ": [
                        "1722",
                        "1422",
                        "1335",
                        "1325",
                        "1311"
                    ],
                    "kda": "0/3/7",
                    "money": "5873",
                    "damage": "26443",
                    "endure": "78858"
                }
            ]
        }
    }
]